{"id":"KZH83BXYMZE9D","name":"Review Icons - 17,095 free icons","size":35144,"btime":1644512181061,"mtime":1644512181061,"ext":"png","tags":[],"folders":["KZYMNMNN5BWOW"],"isDeleted":false,"url":"https://www.flaticon.com/free-icon/rating_1484560?term=review&page=1&position=59&page=1&position=59&related_id=1484560&origin=tag","annotation":"","modificationTime":1644512181046,"width":512,"height":512,"noThumbnail":true,"lastModified":1645564657576,"palettes":[{"color":[251,183,43],"ratio":58},{"color":[37,29,36],"ratio":34},{"color":[36,28,28],"ratio":2.55},{"color":[169,122,36],"ratio":1.34},{"color":[105,79,36],"ratio":1},{"color":[84,172,212],"ratio":0.67},{"color":[108,204,108],"ratio":0.55}]}