{"id":"KZH8EETIWCSX1","name":"Core Dashboard Builder – Home lightdark by Tran Mau Tri Tam ✪ for UI8","size":8838505,"btime":1644512698008,"mtime":1644512700698,"ext":"mp4","tags":[],"folders":["KZYMWSV6IQTDA"],"isDeleted":true,"url":"https://dribbble.com/shots/16958016-Core-Dashboard-Builder-Home-light-dark","annotation":"","modificationTime":1644512697990,"duration":6.528,"height":1800,"width":2400,"lastModified":1645565142240,"palettes":[{"color":[27,28,29],"ratio":68,"$$hashKey":"object:3107"},{"color":[101,115,122],"ratio":14,"$$hashKey":"object:3108"},{"color":[217,219,216],"ratio":13,"$$hashKey":"object:3109"},{"color":[67,70,70],"ratio":1.56,"$$hashKey":"object:3110"},{"color":[75,129,179],"ratio":1.47,"$$hashKey":"object:3111"},{"color":[46,53,60],"ratio":0.68,"$$hashKey":"object:3112"}],"deletedTime":1645565142211}